{
  "name": "Deutsch",
  "prefix": "§6Slime§aUnity §8»§r ",
  "default_chat_color": "§r",

  "message_no_lobby_found": "{prefix} Es konnte keine freie Lobby gefunden werden...",
  "message_unknown_command": "{prefix} §cUnbekannter Command.",
  "message_unknown_player": "{prefix} Spieler konnte nicht gefunden werden.",
  "message_error": "{prefix} Irgendetwas ist schief gelaufen...",
  "message_coins_added": "{prefix} Du hast {target} {coins} Coins gegeben.",
  "message_coins_received": "{prefix} Du hast von {sender} {coins} Coins erhalten.",
  "message_vote_coins_added": "{prefix} Du hast {target} {coins} Votecoins gegeben.",
  "message_vote_coins_received": "{prefix} Du hast von {sender} {coins} Votecoins erhalten.",
  "message_broadcast_successful": "{prefix} Deine Nachricht wurde erfolgreich an alle Server gesendet.",
  "message_chat_cleared": "{prefix} Der Chat wurde von {player} geleert.",
  "message_inventory_cleared": "{prefix} Du hast das Inventar von {target} geleert.",
  "message_enderchest_cleared": "{prefix} Du hast das Inventar von {target} geleert.",
  "message_coins_info": "{prefix} Coins von {target}: {coins}",
  "message_unknown_gamemode": "{prefix} Unbekannter GameMode",
  "message_gamemode_changed_self": "{prefix} Du hast deinen GameMode auf {gamemode} gesetzt.",
  "message_gamemode_changed": "{prefix} Dein GameMode wurde auf {gamemode} gesetzt.",
  "message_gamemode_changed_other": "{prefix} Du hast den GameMode von {target} auf {gamemode} gesetzt.",
  "message_gamemode_changed_see_other": "{prefix} {player} hat den GameMode von {target} auf {gamemode} gesetzt.",
  "message_already_on_server": "{prefix} Du befindest bereits auf diesem Server.",
  "message_player_kicked": "{prefix} Du hast {target} für {reason} gekickt.",
  "message_killed_player": "{prefix} Du hast {player} getötet.",
  "message_unknown_server": "{prefix} Server konnte nicht gefunden werden.",
  "message_tpall": "{prefix} {player} hat alle Spieler zu sich teleportiert.",
  "message_transfer_other": "Transferiere {player} auf Server {server}...",
  "message_transfer": "Transferiere auf Server {server}...",
  "message_settings_saved": "{prefix} Einstellungen wurden erfolgreich gespeichert.",
  "message_joinme": "§7----------------------------------------------\n{player} hat ein JoinMe auf {server} erstellt.\nNutze /joinme um nachzuspringen\n§7----------------------------------------------",
  "no_proxy_login": "Du bist nicht in der Proxy eingeloggt.",
  "server_restarting": "§eServer wird neugestartet!",

  "title_joinme": "§lJoinMe",
  "button_create_joinme": "JoinMe erstellen",

  "title_settings": "§lEinstellungen",
  "dropdown_language": "§aSprache",
  "toggle_party_requests": "§aPartyanfragen",
  "toggle_friend_requests": "§aFreundschaftsanfragen",
  "toggle_clan_requests": "§aClananfragen",
  "toggle_friend_jump": "§aFreunde können Nachspringen",
  "toggle_private_messages": "§aPrivat Nachrichten",
  "toggle_autonick": "§aAuto Nick"
}